tensorhub/__init__.py
tensorhub/layers/__init__.py
tensorhub/layers/layer_wrapper/__init__.py
tensorhub/layers/layer_wrapper/bahdanau_attention.py
tensorhub/layers/layer_wrapper/basic_layers.py
tensorhub/layers/layer_wrapper/inception_layers.py
tensorhub/layers/layer_wrapper/luong_attention.py
tensorhub/models/__init__.py
tensorhub/models/image/__init__.py
tensorhub/models/image/classifiers/__init__.py
tensorhub/models/image/classifiers/classification_wrapper/__init__.py
tensorhub/models/image/classifiers/classification_wrapper/cnn_classifier.py
tensorhub/models/image/classifiers/classification_wrapper/model_tail.py
tensorhub/models/image/classifiers/classification_wrapper/transfer_learning.py
tensorhub/models/text/__init__.py
tensorhub/models/text/classifiers/__init__.py
tensorhub/models/text/classifiers/classification_wrapper/__init__.py
tensorhub/models/text/classifiers/classification_wrapper/perceptron_classifier.py
tensorhub/models/text/classifiers/classification_wrapper/rnn_classifier.py
tensorhub/utilities/__init__.py
tensorhub/utilities/activations.py
tensorhub/utilities/processor.py
tensorhub-1.0.0a4.dist-info/LICENSE
tensorhub-1.0.0a4.dist-info/METADATA
tensorhub-1.0.0a4.dist-info/WHEEL
tensorhub-1.0.0a4.dist-info/top_level.txt
tensorhub-1.0.0a4.dist-info/RECORD
